dstack_bot/__init__.py
dstack_bot/exceptions.py
dstack_bot/main.py
dstack_bot/tasks.py
dstack_bot/utils.py
dstack_bot-1.1.9.dist-info/METADATA
dstack_bot-1.1.9.dist-info/WHEEL
dstack_bot-1.1.9.dist-info/entry_points.txt
dstack_bot-1.1.9.dist-info/top_level.txt
dstack_bot-1.1.9.dist-info/zip-safe
dstack_bot-1.1.9.dist-info/RECORD
